examples/__init__.py
examples/send_email.py
isend/__init__.py
isend/client.py
isend_ai-1.0.0.dist-info/licenses/LICENSE
tests/__init__.py
tests/test_client.py
isend_ai-1.0.0.dist-info/METADATA
isend_ai-1.0.0.dist-info/WHEEL
isend_ai-1.0.0.dist-info/top_level.txt
isend_ai-1.0.0.dist-info/RECORD
