Metadata-Version: 2.4
Name: isend-ai
Version: 1.0.0
Summary: Python SDK for isend.ai - Send emails easily using email connectors like SES, SendGrid, and more
Home-page: https://github.com/isend-ai/python-sdk
Author: isend.ai
Author-email: "isend.ai" <support@isend.ai>
License: MIT
Project-URL: Homepage, https://github.com/isend-ai/python-sdk
Project-URL: Repository, https://github.com/isend-ai/python-sdk
Project-URL: Documentation, https://github.com/isend-ai/python-sdk#readme
Project-URL: Bug Tracker, https://github.com/isend-ai/python-sdk/issues
Keywords: isend,email,sdk,ses,sendgrid,mailgun,postmark
Classifier: Development Status :: 5 - Production/Stable
Classifier: Intended Audience :: Developers
Classifier: License :: OSI Approved :: MIT License
Classifier: Operating System :: OS Independent
Classifier: Programming Language :: Python :: 3
Classifier: Programming Language :: Python :: 3.6
Classifier: Programming Language :: Python :: 3.7
Classifier: Programming Language :: Python :: 3.8
Classifier: Programming Language :: Python :: 3.9
Classifier: Programming Language :: Python :: 3.10
Classifier: Programming Language :: Python :: 3.11
Classifier: Topic :: Communications :: Email
Classifier: Topic :: Software Development :: Libraries :: Python Modules
Requires-Python: >=3.6
License-File: LICENSE
Requires-Dist: requests>=2.25.0
Provides-Extra: dev
Requires-Dist: pytest>=6.0.0; extra == "dev"
Requires-Dist: pytest-cov>=2.10.0; extra == "dev"
Requires-Dist: black>=21.0.0; extra == "dev"
Requires-Dist: flake8>=3.8.0; extra == "dev"
Requires-Dist: mypy>=0.800; extra == "dev"
Dynamic: author
Dynamic: home-page
Dynamic: license-file
Dynamic: requires-python
